mltunex/__init__.py
mltunex/main.py
mltunex/ai_handler/__init__.py
mltunex/ai_handler/metadata_profiler.py
mltunex/ai_handler/prompt.py
mltunex/ai_handler/llm_manager/__init__.py
mltunex/ai_handler/llm_manager/groq_handler.py
mltunex/ai_handler/llm_manager/llm_manager.py
mltunex/ai_handler/llm_manager/openai_handler.py
mltunex/config/__init__.py
mltunex/config/config.py
mltunex/config/llm_config.py
mltunex/data/__init__.py
mltunex/data/base.py
mltunex/data/ingestion.py
mltunex/data/loader.py
mltunex/data/splitter.py
mltunex/evaluate/__init__.py
mltunex/evaluate/base.py
mltunex/evaluate/evaluate_model.py
mltunex/evaluate/metrics_registry.py
mltunex/hyperparam_tuner/__init__.py
mltunex/hyperparam_tuner/base.py
mltunex/hyperparam_tuner/hyperparameter_tuner.py
mltunex/hyperparam_tuner/hyperparameter_tuning_orchestration.py
mltunex/hyperparam_tuner/optuna_tuner.py
mltunex/library_trainer/__init__.py
mltunex/library_trainer/base.py
mltunex/library_trainer/library_trainer.py
mltunex/library_trainer/sklearn_trainer.py
mltunex/model_registry/__init__.py
mltunex/model_registry/base.py
mltunex/model_registry/model_registry.py
mltunex/model_registry/sklearn_registry.py
mltunex/trainer/__init__.py
mltunex/trainer/base.py
mltunex/trainer/trainer.py
mltunex/training_strategy/__init__.py
mltunex/training_strategy/iteration_strategy.py
mltunex/training_strategy/parallelization_strategy.py
mltunex/utils/__init__.py
mltunex/utils/model_utils.py
mltunex-0.1.7.dist-info/METADATA
mltunex-0.1.7.dist-info/WHEEL
mltunex-0.1.7.dist-info/top_level.txt
mltunex-0.1.7.dist-info/RECORD
