Metadata-Version: 2.4
Name: MLTuneX
Version: 0.1.7
Summary: A package for machine learning tuning and optimization.
Home-page: https://github.com/ayuk007/MLTuneX
Author: Ayush Nashine
Author-email: ayush.nashine@gmail.com
Requires-Python: >=3.8
Requires-Dist: scikit-learn
Requires-Dist: pandas
Requires-Dist: numpy
Requires-Dist: langchain
Requires-Dist: openai
Requires-Dist: langchain-openai
Requires-Dist: langchain-community
Requires-Dist: langchain-core
Requires-Dist: optuna
Requires-Dist: python-dotenv
Requires-Dist: json_repair
Requires-Dist: langchain-groq
Dynamic: author
Dynamic: author-email
Dynamic: description
Dynamic: description-content-type
Dynamic: home-page
Dynamic: requires-dist
Dynamic: requires-python
Dynamic: summary
